logseg/__init__.py
logseg/globals.py
logseg/log_setup.py
logseg/project_metadata.py
logseg/utils.py
logseg/configurations/__init__.py
logseg/configurations/config.py
logseg-0.3.0.dist-info/licenses/LICENSE
logseg-0.3.0.dist-info/METADATA
logseg-0.3.0.dist-info/WHEEL
logseg-0.3.0.dist-info/top_level.txt
logseg-0.3.0.dist-info/RECORD
